{
  "level_code": "NH",
  "topic_slug": "talk-about-my-living-arrangements",
  "topic_title": "talk about my living arrangements.",
  "can_do_statement": "I can talk about my living arrangements.",
  "lessons": [
    {
      "slug": "types-of-housing",
      "title": "Types of Housing",
      "objective": "Identify different types of housing and say where you live.",
      "cards": [
        {
          "front": "la casa",
          "back": "the house",
          "ipa": "/la ˈka.sa/",
          "example_sentence": "Vivo en la casa con mi familia.",
          "grammar_explanation": "Feminine noun. 'La' is the definite article."
        },
        {
          "front": "el apartamento",
          "back": "the apartment",
          "ipa": "/el a.paɾ.ta.ˈmen.to/",
          "example_sentence": "Ella vive en un apartamento pequeño.",
          "grammar_explanation": "Masculine noun. 'El' is the definite article."
        },
        {
          "front": "la residencia estudiantil",
          "back": "the dorm",
          "ipa": "/la re.si.ˈðen.θja es.tu.ˈðjan.til/",
          "example_sentence": "Muchos estudiantes viven en la residencia estudiantil.",
          "grammar_explanation": "Feminine noun. 'La' is the definite article."
        },
        {
          "front": "la habitación",
          "back": "the room",
          "ipa": "/la a.βi.ta.ˈθjon/",
          "example_sentence": "Mi habitación es muy grande.",
          "grammar_explanation": "Feminine noun. 'La' is the definite article."
        },
        {
          "front": "la vivienda",
          "back": "the housing/dwelling",
          "ipa": "/la bi.ˈβjen.da/",
          "example_sentence": "Necesito encontrar una vivienda cerca del trabajo.",
          "grammar_explanation": "Feminine noun. 'La' is the definite article."
        },
        {
          "front": "el edificio",
          "back": "the building",
          "ipa": "/el e.ði.ˈfi.θjo/",
          "example_sentence": "El edificio es muy alto.",
          "grammar_explanation": "Masculine noun. 'El' is the definite article."
        },
        {
          "front": "el piso",
          "back": "the floor/apartment (Spain)",
          "ipa": "/el ˈpi.so/",
          "example_sentence": "Vivo en el piso diez.",
          "grammar_explanation": "Masculine noun. 'El' is the definite article."
        },
        {
          "front": "compartir",
          "back": "to share",
          "ipa": "/kom.paɾ.ˈtiɾ/",
          "example_sentence": "Quiero compartir un piso con mis amigos.",
          "grammar_explanation": "Regular -ir verb."
        }
      ]
    },
    {
      "slug": "rooms-of-the-house",
      "title": "Rooms of the House",
      "objective": "Name different rooms in a house or apartment.",
      "cards": [
        {
          "front": "el dormitorio",
          "back": "the bedroom",
          "ipa": "/el doɾ.mi.ˈto.ɾjo/",
          "example_sentence": "Mi dormitorio es pequeño pero cómodo.",
          "grammar_explanation": "Masculine noun. 'El' is the definite article."
        },
        {
          "front": "la cocina",
          "back": "the kitchen",
          "ipa": "/la ko.ˈθi.na/",
          "example_sentence": "Me gusta cocinar en la cocina.",
          "grammar_explanation": "Feminine noun. 'La' is the definite article."
        },
        {
          "front": "el baño",
          "back": "the bathroom",
          "ipa": "/el ˈba.ɲo/",
          "example_sentence": "El baño está cerca del dormitorio.",
          "grammar_explanation": "Masculine noun. 'El' is the definite article."
        },
        {
          "front": "la sala",
          "back": "the living room",
          "ipa": "/la ˈsa.la/",
          "example_sentence": "Vemos la televisión en la sala.",
          "grammar_explanation": "Feminine noun. 'La' is the definite article."
        },
        {
          "front": "el comedor",
          "back": "the dining room",
          "ipa": "/el ko.me.ˈðoɾ/",
          "example_sentence": "Comemos juntos en el comedor.",
          "grammar_explanation": "Masculine noun. 'El' is the definite article."
        },
        {
          "front": "el balcón",
          "back": "the balcony",
          "ipa": "/el bal.ˈkon/",
          "example_sentence": "Me gusta leer en el balcón.",
          "grammar_explanation": "Masculine noun. 'El' is the definite article."
        },
        {
          "front": "el jardín",
          "back": "the garden",
          "ipa": "/el xaɾ.ˈðin/",
          "example_sentence": "Tenemos flores en el jardín.",
          "grammar_explanation": "Masculine noun. 'El' is the definite article."
        },
        {
          "front": "el garaje",
          "back": "the garage",
          "ipa": "/el ɡa.ˈɾa.xe/",
          "example_sentence": "Guardamos el coche en el garaje.",
          "grammar_explanation": "Masculine noun. 'El' is the definite article."
        },
        {
          "front": "el pasillo",
          "back": "the hallway",
          "ipa": "/el pa.ˈsi.ʎo/",
          "example_sentence": "El pasillo conecta todas las habitaciones.",
          "grammar_explanation": "Masculine noun. 'El' is the definite article."
        }
      ]
    },
    {
      "slug": "furniture-and-appliances",
      "title": "Furniture and Appliances",
      "objective": "Identify common furniture and appliances found in a home.",
      "cards": [
        {
          "front": "la cama",
          "back": "the bed",
          "ipa": "/la ˈka.ma/",
          "example_sentence": "Duermo en la cama.",
          "grammar_explanation": "Feminine noun. 'La' is the definite article."
        },
        {
          "front": "la mesa",
          "back": "the table",
          "ipa": "/la ˈme.sa/",
          "example_sentence": "Comemos en la mesa.",
          "grammar_explanation": "Feminine noun. 'La' is the definite article."
        },
        {
          "front": "la silla",
          "back": "the chair",
          "ipa": "/la ˈsi.ʎa/",
          "example_sentence": "Me siento en la silla.",
          "grammar_explanation": "Feminine noun. 'La' is the definite article."
        },
        {
          "front": "el sofá",
          "back": "the sofa",
          "ipa": "/el so.ˈfa/",
          "example_sentence": "Me relajo en el sofá.",
          "grammar_explanation": "Masculine noun. 'El' is the definite article."
        },
        {
          "front": "la nevera",
          "back": "the refrigerator",
          "ipa": "/la ne.ˈβe.ɾa/",
          "example_sentence": "Hay comida en la nevera.",
          "grammar_explanation": "Feminine noun. 'La' is the definite article. Also known as 'el refrigerador'."
        },
        {
          "front": "el horno",
          "back": "the oven",
          "ipa": "/el ˈoɾ.no/",
          "example_sentence": "Cocino pan en el horno.",
          "grammar_explanation": "Masculine noun. 'El' is the definite article."
        },
        {
          "front": "la lámpara",
          "back": "the lamp",
          "ipa": "/la ˈlam.pa.ɾa/",
          "example_sentence": "La lámpara ilumina la habitación.",
          "grammar_explanation": "Feminine noun. 'La' is the definite article."
        },
        {
          "front": "el televisor",
          "back": "the television",
          "ipa": "/el te.le.βi.ˈsoɾ/",
          "example_sentence": "Vemos películas en el televisor.",
          "grammar_explanation": "Masculine noun. 'El' is the definite article."
        },
        {
          "front": "el armario",
          "back": "the closet",
          "ipa": "/el aɾ.ˈma.ɾjo/",
          "example_sentence": "Guardo mi ropa en el armario.",
          "grammar_explanation": "Masculine noun. 'El' is the definite article."
        },
        {
          "front": "la lavadora",
          "back": "the washing machine",
          "ipa": "/la la.βa.ˈðo.ɾa/",
          "example_sentence": "Lavo la ropa en la lavadora.",
          "grammar_explanation": "Feminine noun. 'La' is the definite article."
        }
      ]
    },
    {
      "slug": "describing-your-home",
      "title": "Describing Your Home",
      "objective": "Use adjectives to describe your living arrangements.",
      "cards": [
        {
          "front": "grande",
          "back": "big/large",
          "ipa": "/ˈɡɾan.de/",
          "example_sentence": "Mi casa es grande.",
          "grammar_explanation": "Adjective. Can be used before or after the noun, but placement after is more common. Agrees in number and gender when placed before a noun."
        },
        {
          "front": "pequeño/a",
          "back": "small",
          "ipa": "/pe.ˈke.ɲo/",
          "example_sentence": "Mi apartamento es pequeño.",
          "grammar_explanation": "Adjective. Agrees in gender and number with the noun it modifies."
        },
        {
          "front": "cómodo/a",
          "back": "comfortable",
          "ipa": "/ˈko.mo.do/",
          "example_sentence": "El sofá es muy cómodo.",
          "grammar_explanation": "Adjective. Agrees in gender and number with the noun it modifies."
        },
        {
          "front": "moderno/a",
          "back": "modern",
          "ipa": "/mo.ˈðeɾ.no/",
          "example_sentence": "La cocina es moderna.",
          "grammar_explanation": "Adjective. Agrees in gender and number with the noun it modifies."
        },
        {
          "front": "antiguo/a",
          "back": "old/antique",
          "ipa": "/an.ˈti.ɣwo/",
          "example_sentence": "La casa es antigua.",
          "grammar_explanation": "Adjective. Agrees in gender and number with the noun it modifies."
        },
        {
          "front": "limpio/a",
          "back": "clean",
          "ipa": "/ˈlim.pjo/",
          "example_sentence": "El baño está limpio.",
          "grammar_explanation": "Adjective. Agrees in gender and number with the noun it modifies."
        },
        {
          "front": "sucio/a",
          "back": "dirty",
          "ipa": "/ˈsu.θjo/",
          "example_sentence": "El piso está sucio.",
          "grammar_explanation": "Adjective. Agrees in gender and number with the noun it modifies."
        },
        {
          "front": "bonito/a",
          "back": "pretty/beautiful",
          "ipa": "/bo.ˈni.to/",
          "example_sentence": "Mi casa es bonita.",
          "grammar_explanation": "Adjective. Agrees in gender and number with the noun it modifies."
        },
        {
          "front": "nuevo/a",
          "back": "new",
          "ipa": "/ˈnwe.βo/",
          "example_sentence": "Tengo un apartamento nuevo.",
          "grammar_explanation": "Adjective. Agrees in gender and number with the noun it modifies."
        }
      ]
    },
    {
      "slug": "location-and-neighborhood",
      "title": "Location and Neighborhood",
      "objective": "Describe the location of your home and neighborhood.",
      "cards": [
        {
          "front": "cerca de",
          "back": "near/close to",
          "ipa": "/ˈθeɾ.ka ðe/",
          "example_sentence": "Mi casa está cerca de la escuela.",
          "grammar_explanation": "Prepositional phrase."
        },
        {
          "front": "lejos de",
          "back": "far from",
          "ipa": "/ˈle.xos ðe/",
          "example_sentence": "El supermercado está lejos de mi casa.",
          "grammar_explanation": "Prepositional phrase."
        },
        {
          "front": "en el centro",
          "back": "in the center/downtown",
          "ipa": "/en el ˈθen.tɾo/",
          "example_sentence": "Vivo en el centro de la ciudad.",
          "grammar_explanation": "Prepositional phrase."
        },
        {
          "front": "en las afueras",
          "back": "in the suburbs",
          "ipa": "/en las a.ˈfwe.ɾas/",
          "example_sentence": "Mis padres viven en las afueras.",
          "grammar_explanation": "Prepositional phrase."
        },
        {
          "front": "tranquilo/a",
          "back": "quiet/peaceful",
          "ipa": "/tɾaŋ.ˈki.lo/",
          "example_sentence": "Mi barrio es tranquilo.",
          "grammar_explanation": "Adjective. Agrees in gender and number with the noun it modifies."
        },
        {
          "front": "ruidoso/a",
          "back": "noisy",
          "ipa": "/rwi.ˈðo.so/",
          "example_sentence": "El centro es ruidoso.",
          "grammar_explanation": "Adjective. Agrees in gender and number with the noun it modifies."
        },
        {
          "front": "seguro/a",
          "back": "safe",
          "ipa": "/se.ˈɣu.ɾo/",
          "example_sentence": "Mi barrio es seguro.",
          "grammar_explanation": "Adjective. Agrees in gender and number with the noun it modifies."
        },
        {
          "front": "peligroso/a",
          "back": "dangerous",
          "ipa": "/pe.li.ˈɣɾo.so/",
          "example_sentence": "Algunas calles son peligrosas.",
          "grammar_explanation": "Adjective. Agrees in gender and number with the noun it modifies."
        },
        {
          "front": "el barrio",
          "back": "the neighborhood",
          "ipa": "/el ˈba.rjo/",
          "example_sentence": "Me gusta mi barrio.",
          "grammar_explanation": "Masculine noun. 'El' is the definite article."
        }
      ]
    },
    {
      "slug": "who-do-you-live-with",
      "title": "Who Do You Live With?",
      "objective": "Talk about who you live with.",
      "cards": [
        {
          "front": "vivo solo/a",
          "back": "I live alone",
          "ipa": "/ˈbi.βo ˈso.lo/",
          "example_sentence": "Vivo solo en mi apartamento.",
          "grammar_explanation": "Verb conjugation and adjective agreement."
        },
        {
          "front": "vivo con",
          "back": "I live with",
          "ipa": "/ˈbi.βo kon/",
          "example_sentence": "Vivo con mis padres.",
          "grammar_explanation": "Verb conjugation and preposition."
        },
        {
          "front": "mi familia",
          "back": "my family",
          "ipa": "/mi fa.ˈmi.lja/",
          "example_sentence": "Vivo con mi familia.",
          "grammar_explanation": "Noun phrase, possessive adjective."
        },
        {
          "front": "mis compañeros de piso",
          "back": "my roommates",
          "ipa": "/mis kom.pa.ˈɲe.ɾos de ˈpi.so/",
          "example_sentence": "Vivo con mis compañeros de piso.",
          "grammar_explanation": "Noun phrase, plural, possessive adjective."
        },
        {
          "front": "mis padres",
          "back": "my parents",
          "ipa": "/mis ˈpa.ðɾes/",
          "example_sentence": "Vivo con mis padres.",
          "grammar_explanation": "Plural noun, possessive adjective."
        },
        {
          "front": "mi hermano/a",
          "back": "my brother/sister",
          "ipa": "/mi eɾ.ˈma.no/",
          "example_sentence": "Vivo con mi hermano.",
          "grammar_explanation": "Singular noun, possessive adjective."
        },
        {
          "front": "mi amigo/a",
          "back": "my friend",
          "ipa": "/mi a.ˈmi.ɣo/",
          "example_sentence": "Vivo con mi amigo.",
          "grammar_explanation": "Singular noun, possessive adjective."
        },
        {
          "front": "nadie",
          "back": "nobody/no one",
          "ipa": "/ˈna.ðje/",
          "example_sentence": "Vivo solo, no vivo con nadie.",
          "grammar_explanation": "Pronoun."
        },
        {
          "front": "alquilar",
          "back": "to rent",
          "ipa": "/al.ki.ˈlaɾ/",
          "example_sentence": "Tengo que alquilar un apartamento.",
          "grammar_explanation": "Regular -ar verb."
        }
      ]
    }
  ]
}